[
  {
    "id": 9,
    "name": "dough",
    "sumOfKcalPer100g": 34,
    "sumOfFatPer100g": 0.0,
    "sumOfCarbohydratesPer100g": 60.0,
    "sumOfProteinPer100g": 1.0,
    "productsNameList": [
      "water",
      "flour"
    ]
  },
  {
    "id": 10,
    "name": "new dish",
    "sumOfKcalPer100g": 200,
    "sumOfFatPer100g": 0.0,
    "sumOfCarbohydratesPer100g": 0.0,
    "sumOfProteinPer100g": 0.0,
    "productsNameList": [
      "kaako",
      "kaako"
    ]
  },
  {
    "id": 11,
    "name": "Weird dough",
    "sumOfKcalPer100g": 0,
    "sumOfFatPer100g": 0.0,
    "sumOfCarbohydratesPer100g": 0.0,
    "sumOfProteinPer100g": 0.0,
    "productsNameList": [
      "water",
      "Palm oil",
      "flour"
    ]
  }
]